flaked/__init__.py
flaked/cli.py
flaked/plugins/__init__.py
flaked/plugins/flaked_shire.py
flaked-0.2.1.dist-info/LICENSE
flaked-0.2.1.dist-info/METADATA
flaked-0.2.1.dist-info/WHEEL
flaked-0.2.1.dist-info/entry_points.txt
flaked-0.2.1.dist-info/top_level.txt
flaked-0.2.1.dist-info/RECORD
